PySerpentine/__init__.py
PySerpentine/main.py
PySerpentine-1.0.dist-info/METADATA
PySerpentine-1.0.dist-info/WHEEL
PySerpentine-1.0.dist-info/top_level.txt
PySerpentine-1.0.dist-info/RECORD
